{"id":"5e9c0b5d774c2610387e52fa","artists":["5e9b695d7a1236eccfeb26e0"],"title":"Video: Washed Out – A Dedication","content":"<p>Far and away my favourite track from <strong>Washed Out’s</strong> 2011 album <strong><em>Within and Without</em></strong>, <em>A Dedication</em> is thoroughly deserving of a stunning video, and <a href=\"https://www.</p><p>yoonhapark.com/\" target=\"_blank\"><strong>Yoonha Park</strong></a> has created just that. Echoing the delicate, ballad inspired atmosphere of the track, it’s ever-so cliched yet in an entirely watchable way. So there’s shots of people jumping into lakes, water running down windowpanes and plenty other ‘deep and meaningful’ clips, but c’mon, everyone likes a bit of self-indulgence once in a while.</p>\n<p><iframe width=\"560\" height=\"315\" src=\"https://www.youtube.com/embed/noS61QN9nag\" frameborder=\"0\" allowfullscreen></iframe></p>\n","slug":"17621-video-washed-out-a-dedication","category":"music","date":1343853233000,"wpid":17621,"isSticky":false,"featured_image":null,"createdAt":1587284829039,"updatedAt":1588441775126,"author":"5e9b68b27a1236eccfeb1d27","old_image":"generated/e0d224d5c9a962518e7f2482e0b8d626aea9a061.jpg","categories":["music","videos"]}