{"id":"5e9c0aec774c2610387e527f","artists":["5e9b69257a1236eccfeb2332"],"title":"Video: Mmoths – Over You","content":"<p>Hugely hyped shows all over the world, a mightily successful EP and now an exclusive track on Annie Mac’s AMP 2012 Compilation, alongside the likes of <strong>Azealia Banks</strong>, <strong>Diplo</strong> and <strong>Netsky</strong>; it’s fair to say that Irish beatmaker <strong>Mmoths</strong> is kicking up quite a fuss.</p><p> The tune in question, <em>Over You</em>, is precisely what we’ve come to expect from the teenager, atmospheric and club-friendly, yet maintaining a vivid personality. The visuals come from <a href=\"https://www.feelgoodlost.me/\" target=\"_blank\">Feel Good Lost</a>, check it out below.</p>\n<p><iframe src=\"https://www.youtube.com/embed/rrn-APyt-DY\" frameborder=\"0\" width=\"560\" height=\"315\"></iframe></p>\n","slug":"17880-video-mmoths-over-you","category":"music","date":1347390339000,"wpid":17880,"isSticky":false,"featured_image":null,"createdAt":1587284716240,"updatedAt":1588441774807,"author":"5e9b68b27a1236eccfeb1d27","old_image":"2012/09/screen-shot-2012-09-11-at-21.03.34-950x366.png","categories":["music","new","videos"]}