{"id":"5e9c062f774c2610387e4e40","artists":["5e9b68d47a1236eccfeb1e34"],"title":"New: Benin City – Faithless","content":"<p>Oh HEY.</p><p> It’s nearly festival season, so what better to celebrate the turn of the seasons than with this euphoric, ecstasy ridden new jam from <strong>Benin City</strong>?</p>\n<p>I don’t know if I can answer that question, but what I do know is that <em>Disappear</em>, the cut in question, is probably one of the most festival ready tunes I’ve heard in a long time. Now it’s funny I should mention that because <strong>Benin City</strong> are headlining <strong>Brainchild Festival</strong>, our sister/mother/brother collaboration ‘thing’.</p>\n<p>They’ll probably play this, that’s worth £50.</p>\n<p><a href=\"https://brainchildfestival.co.uk/admission\">grab tickets here.</a></p>\n<p><iframe src=\"https://w.soundcloud.com/player/?url=http%3A%2F%2Fapi.soundcloud.com%2Ftracks%2F91234393\" height=\"166\" width=\"100%\" frameborder=\"no\" scrolling=\"no\"></iframe></p>\n","slug":"21919-new-benin-city-faithless","category":"music","date":1368727792000,"wpid":21919,"isSticky":false,"featured_image":null,"createdAt":1587283503284,"updatedAt":1588441766423,"author":"5e9b68b27a1236eccfeb1d24","old_image":"generated/7f52e59dfb5c9e38ce1ef34057b24ebf76ab3979.jpg","categories":["music","new","newnews"]}