{"id":"5e9c0556774c2610387e4d7e","artists":["5e9b69577a1236eccfeb265d"],"title":"New: Thigh Master – D.D.","content":"<p>Australia coming up trumps yet again, with Brisbane trio<strong> Thigh Master </strong>cranking it up.</p><p> Scuzzy<strong> Buzzcocks</strong> meets<strong> The Libertines</strong> ‘pop hitz’ (their words, not mine), D.D., the B-side to their upcoming single, Head of the Witch, is a three minute blast through almost every rock and roll key influencer of the past forty years. Raw vocals, relatively simplistic guitar lines, it’s something NME might have pedalled… back when NME was good. Check out D.D. below.</p>\n<p><iframe style=\"border: 0; width: 350px; height: 442px;\" src=\"https://bandcamp.com/EmbeddedPlayer/track=399591022/size=large/bgcol=ffffff/linkcol=0687f5/notracklist=true/transparent=true/\" height=\"240\" width=\"320\" seamless=\"\"></iframe></p>\n","slug":"22998-new-thigh-master-d-d","category":"mpfree","date":1373570815000,"wpid":22998,"isSticky":false,"featured_image":null,"createdAt":1587283286154,"updatedAt":1588441764531,"author":"5e9b68b27a1236eccfeb1d27","old_image":"generated/8ce56d8a9a901c7fb8a0e6496dd8a16ef5ac0482.jpg","categories":["mpfree","new","music"]}