{"id":"5e9c041f774c2610387e4bfa","artists":["5e9b69637a1236eccfeb271d"],"title":"New: Woman’s Hour – Darkest Place","content":"<p>I’m a sucker for this sort of pop.</p><p> Lethargic synths and wistful female vocals, London quartet <strong>Woman’s Hour</strong> tug on the heartstrings with their latest offering, <em>Darkest Place</em>. Twisting and turning before collapsing into a swirling haze of delightful ‘ooo’s and tinkling keys, it’s their most enticing outing to date. Check out<em> Darkest Place</em> below, and keep up with the quartet via <a href=\"https://www.facebook.com/womanshourband\" target=\"_blank\">Facebook</a>.</p>\n<p><iframe src=\"https://w.soundcloud.com/player/?url=http%3A%2F%2Fapi.soundcloud.com%2Ftracks%2F109692766\" height=\"166\" width=\"100%\" frameborder=\"no\" scrolling=\"no\"></iframe></p>\n","slug":"24245-new-womans-hour-darkest-place","category":"music","date":1379077050000,"wpid":24245,"isSticky":false,"featured_image":null,"createdAt":1587282975878,"updatedAt":1588441762613,"author":"5e9b68b27a1236eccfeb1d27","old_image":"generated/b6f8041814623b24740177955a84afc189382c6b.jpg","categories":["music","new"]}