{"id":"5e9c00fd774c2610387e4709","artists":["5e9b69317a1236eccfeb23ff"],"title":"New: Palm Honey – Palace","content":"<p>Here’s some woozy, Tame Impala indebted psych-pop for you, from Reading quartet <strong>Palm Honey</strong>.</p><p> With the summer months (hopefuly) just round the corner, and festival season kicking into gear in the coming weeks, it may be a little early for these guys to make an impact this year, but this is definitely the sort of sound and ambition that takes you to those sort of stages. Check out <em>Palace</em> below.</p>\n","slug":"28103-new-palm-honey-palace","category":"music","date":1398619375000,"wpid":28103,"isSticky":false,"featured_image":null,"createdAt":1587282173902,"updatedAt":1588441757912,"author":"5e9b68b27a1236eccfeb1d27","old_image":"generated/fa28590a4b80937507d62126e7a63e36b6ae009a.jpg","categories":["music","new"]}